<?xml version="1.0" encoding="UTF-8" ?>
<!DOCTYPE mapper PUBLIC "-//mybatis.org//DTD Mapper 3.0//EN" "http://mybatis.org/dtd/mybatis-3-mapper.dtd" >
<mapper namespace="com.addoiles.dao.OilShareMapper" >
  <resultMap id="BaseResultMap" type="com.addoiles.entity.OilShare" >
    <!--
      WARNING - @mbggenerated
      This element is automatically generated by MyBatis Generator, do not modify.
      This element was generated on Tue Jul 18 00:32:24 CST 2017.
    -->
    <id column="id" property="id" jdbcType="VARCHAR" />
    <result column="title" property="title" jdbcType="VARCHAR" />
    <result column="content" property="content" jdbcType="VARCHAR" />
    <result column="favorite" property="favorite" jdbcType="INTEGER" />
    <result column="dislike" property="dislike" jdbcType="INTEGER" />
    <result column="delete_status" property="delete_status" jdbcType="INTEGER" />
  </resultMap>
  <sql id="Base_Column_List" >
    <!--
      WARNING - @mbggenerated
      This element is automatically generated by MyBatis Generator, do not modify.
      This element was generated on Tue Jul 18 00:32:24 CST 2017.
    -->
    id, title, content, favorite, dislike, delete_status
  </sql>
  <select id="selectByPrimaryKey" resultMap="BaseResultMap" parameterType="java.lang.String" >
    <!--
      WARNING - @mbggenerated
      This element is automatically generated by MyBatis Generator, do not modify.
      This element was generated on Tue Jul 18 00:32:24 CST 2017.
    -->
    select 
    <include refid="Base_Column_List" />
    from oil_share
    where id = #{id,jdbcType=VARCHAR}
  </select>
  <delete id="deleteByPrimaryKey" parameterType="java.lang.String" >
    <!--
      WARNING - @mbggenerated
      This element is automatically generated by MyBatis Generator, do not modify.
      This element was generated on Tue Jul 18 00:32:24 CST 2017.
    -->
    delete from oil_share
    where id = #{id,jdbcType=VARCHAR}
  </delete>
  <insert id="insert" parameterType="com.addoiles.entity.OilShare" >
    <!--
      WARNING - @mbggenerated
      This element is automatically generated by MyBatis Generator, do not modify.
      This element was generated on Tue Jul 18 00:32:24 CST 2017.
    -->
    insert into oil_share (id, title, content, 
      favorite, dislike, delete_status
      )
    values (#{id,jdbcType=VARCHAR}, #{title,jdbcType=VARCHAR}, #{content,jdbcType=VARCHAR}, 
      #{favorite,jdbcType=INTEGER}, #{dislike,jdbcType=INTEGER}, #{delete_status,jdbcType=INTEGER}
      )
  </insert>
  <insert id="insertSelective" parameterType="com.addoiles.entity.OilShare" >
    <!--
      WARNING - @mbggenerated
      This element is automatically generated by MyBatis Generator, do not modify.
      This element was generated on Tue Jul 18 00:32:24 CST 2017.
    -->
    insert into oil_share
    <trim prefix="(" suffix=")" suffixOverrides="," >
      <if test="id != null" >
        id,
      </if>
      <if test="title != null" >
        title,
      </if>
      <if test="content != null" >
        content,
      </if>
      <if test="favorite != null" >
        favorite,
      </if>
      <if test="dislike != null" >
        dislike,
      </if>
      <if test="delete_status != null" >
        delete_status,
      </if>
    </trim>
    <trim prefix="values (" suffix=")" suffixOverrides="," >
      <if test="id != null" >
        #{id,jdbcType=VARCHAR},
      </if>
      <if test="title != null" >
        #{title,jdbcType=VARCHAR},
      </if>
      <if test="content != null" >
        #{content,jdbcType=VARCHAR},
      </if>
      <if test="favorite != null" >
        #{favorite,jdbcType=INTEGER},
      </if>
      <if test="dislike != null" >
        #{dislike,jdbcType=INTEGER},
      </if>
      <if test="delete_status != null" >
        #{delete_status,jdbcType=INTEGER},
      </if>
    </trim>
  </insert>
  <update id="updateByPrimaryKeySelective" parameterType="com.addoiles.entity.OilShare" >
    <!--
      WARNING - @mbggenerated
      This element is automatically generated by MyBatis Generator, do not modify.
      This element was generated on Tue Jul 18 00:32:24 CST 2017.
    -->
    update oil_share
    <set >
      <if test="title != null" >
        title = #{title,jdbcType=VARCHAR},
      </if>
      <if test="content != null" >
        content = #{content,jdbcType=VARCHAR},
      </if>
      <if test="favorite != null" >
        favorite = #{favorite,jdbcType=INTEGER},
      </if>
      <if test="dislike != null" >
        dislike = #{dislike,jdbcType=INTEGER},
      </if>
      <if test="delete_status != null" >
        delete_status = #{delete_status,jdbcType=INTEGER},
      </if>
    </set>
    where id = #{id,jdbcType=VARCHAR}
  </update>
  <update id="updateByPrimaryKey" parameterType="com.addoiles.entity.OilShare" >
    <!--
      WARNING - @mbggenerated
      This element is automatically generated by MyBatis Generator, do not modify.
      This element was generated on Tue Jul 18 00:32:24 CST 2017.
    -->
    update oil_share
    set title = #{title,jdbcType=VARCHAR},
      content = #{content,jdbcType=VARCHAR},
      favorite = #{favorite,jdbcType=INTEGER},
      dislike = #{dislike,jdbcType=INTEGER},
      delete_status = #{delete_status,jdbcType=INTEGER}
    where id = #{id,jdbcType=VARCHAR}
  </update>
</mapper>